README.rst
setup.py
collector/__init__.py
collector/datastore.py
knxpy/__init__.py
knxpy/__version__.py
knxpy/core.py
knxpy/ip.py
knxpy/ip_async.py
knxpy/knxd.py
knxpy/knxd_async.py
knxpy/knxd_sh.py
knxpy/util.py
knxpy.egg-info/PKG-INFO
knxpy.egg-info/SOURCES.txt
knxpy.egg-info/dependency_links.txt
knxpy.egg-info/top_level.txt
knxpy/dpts/__init__.py
knxpy/dpts/dpt1.py
knxpy/dpts/dpt10.py
knxpy/dpts/dpt11.py
knxpy/dpts/dpt12.py
knxpy/dpts/dpt13.py
knxpy/dpts/dpt14.py
knxpy/dpts/dpt16000.py
knxpy/dpts/dpt16001.py
knxpy/dpts/dpt17.py
knxpy/dpts/dpt2.py
knxpy/dpts/dpt20.py
knxpy/dpts/dpt232.py
knxpy/dpts/dpt24.py
knxpy/dpts/dpt3.py
knxpy/dpts/dpt4002.py
knxpy/dpts/dpt5.py
knxpy/dpts/dpt5001.py
knxpy/dpts/dpt6.py
knxpy/dpts/dpt7.py
knxpy/dpts/dpt8.py
knxpy/dpts/dpt9.py