Metadata-Version: 1.1
Name: knxpy
Version: 0.2.7
Summary: A simple connector to a KNX bus
Home-page: http://github.com/BrechtBa/knxpy
Author: Daniel Matuschek, Brecht Baeten
Author-email: UNKNOWN
License: MIT
Platform: UNKNOWN
Classifier: Programming Language :: Python :: 3.5
